[{
	"name": "Investor's Group",
	"code": "ig",
	"projects": [
		{
			"name": "Spring Banners",
			"code": "spring_banners",
			"banners": [
				{
					"lang": "en",
					"name": "en_garbage_300x250",
					"width": "300",
					"height": "250"
				}
			]
		}
	] 
},
{
	"name": "CPA",
	"code": "cpa",
	"projects": [
		{
			"name": "Acap",
			"code": "acaf",
			"banners": [
				{
					"lang": "en",
					"name": "en_seek_300x250",
					"width": "300",
					"height": "250"
				},
				{
					"lang": "en",
					"name": "en_seek_300x600",
					"width": "300",
					"height": "600"
				},
				{
					"lang": "en",
					"name": "en_seek_728x90",
					"width": "728x90",
					"height": "90"
				},
				{
					"lang": "en",
					"name": "en_demand_300x250",
					"width": "300",
					"height": "250"
				},
				{
					"lang": "en",
					"name": "en_demand_300x600",
					"width": "300",
					"height": "600"
				},
				{
					"lang": "en",
					"name": "en_demand_728x90",
					"width": "728x90",
					"height": "90"
				},
				{
					"lang": "fr",
					"name": "fr_seek_300x250",
					"width": "300",
					"height": "250"
				},
				{
					"lang": "fr",
					"name": "fr_seek_300x600",
					"width": "300",
					"height": "600"
				},
				{
					"lang": "fr",
					"name": "fr_seek_728x90",
					"width": "728x90",
					"height": "90"
				},
				{
					"lang": "fr",
					"name": "fr_demand_300x250",
					"width": "300",
					"height": "250"
				},
				{
					"lang": "fr",
					"name": "fr_demand_300x600",
					"width": "300",
					"height": "600"
				},
				{
					"lang": "fr",
					"name": "fr_demand_728x90",
					"width": "728x90",
					"height": "90"
				}
			]
		}
	] 
},
{
	"name": "VW",
	"code": "vw",
	"projects": [
		{
			"name": "Tiguan 2018",
			"code": "tiguan2018",
			"banners": [
				{
					"lang": "en",
					"name": "en_3rd_row_seat_bigbox_300x250",
					"width": "300",
					"height": "250"
				},
				{
					"lang": "en",
					"name": "en_3rd_row_seat_bigbox_320x50",
					"width": "320",
					"height": "50"
				},
				{
					"lang": "en",
					"name": "en_3rd_row_seat_bigbox_300x600",
					"width": "300",
					"height": "600"
				},
				{
					"lang": "en",
					"name": "en_3rd_row_seat_bigbox_728x90",
					"width": "728",
					"height": "90"
				},
				{
					"lang": "en",
					"name": "en_cargo_space_bigbox_300x250",
					"width": "300",
					"height": "250"
				},
				{
					"lang": "en",
					"name": "en_cargo_space_bigbox_320x50",
					"width": "320",
					"height": "50"
				},
				{
					"lang": "en",
					"name": "en_cargo_space_bigbox_300x600",
					"width": "300",
					"height": "600"
				},
				{
					"lang": "en",
					"name": "en_cargo_space_bigbox_728x90",
					"width": "728",
					"height": "90"
				},
				{
					"lang": "fr",
					"name": "fr_3rd_row_seat_bigbox_300x250",
					"width": "300",
					"height": "250"
				},
				{
					"lang": "fr",
					"name": "fr_3rd_row_seat_bigbox_320x50",
					"width": "320",
					"height": "50"
				},
				{
					"lang": "fr",
					"name": "fr_3rd_row_seat_bigbox_300x600",
					"width": "300",
					"height": "600"
				},
				{
					"lang": "fr",
					"name": "fr_3rd_row_seat_bigbox_728x90",
					"width": "728",
					"height": "90"
				},
				{
					"lang": "fr",
					"name": "fr_cargo_space_bigbox_300x250",
					"width": "300",
					"height": "250"
				},
				{
					"lang": "fr",
					"name": "fr_cargo_space_bigbox_320x50",
					"width": "320",
					"height": "50"
				},
				{
					"lang": "fr",
					"name": "fr_cargo_space_bigbox_300x600",
					"width": "300",
					"height": "600"
				},
				{
					"lang": "fr",
					"name": "fr_cargo_space_bigbox_728x90",
					"width": "728",
					"height": "90"
				}
			]
		}
	] 
}]